cooltypes/__init__.py
cooltypes/core/CoolInt.py
cooltypes/core/__init__.py
cooltypes/tests/__init__.py
cooltypes/tests/test_CoolInt_a.py
cooltypes/tests/test_CoolInt_b.py
cooltypes-0.1.4.dist-info/licenses/LICENSE.txt
cooltypes-0.1.4.dist-info/METADATA
cooltypes-0.1.4.dist-info/WHEEL
cooltypes-0.1.4.dist-info/top_level.txt
cooltypes-0.1.4.dist-info/RECORD
