Metadata-Version: 2.4
Name: cooltypes
Version: 0.1.4
Summary: This project provides subclasses of popular types well suited for further subclassing.
Author-email: Johannes <johannes-programming@mailfence.com>
License: The MIT License (MIT)
Project-URL: Download, https://pypi.org/project/cooltypes/#files
Project-URL: Index, https://pypi.org/project/cooltypes/
Project-URL: Source, https://github.com/johannes-programming/cooltypes/
Project-URL: Website, https://cooltypes.johannes-programming.online/
Classifier: Development Status :: 3 - Alpha
Classifier: License :: OSI Approved :: MIT License
Classifier: Natural Language :: English
Classifier: Operating System :: OS Independent
Classifier: Programming Language :: Python
Classifier: Programming Language :: Python :: 3
Classifier: Programming Language :: Python :: 3 :: Only
Classifier: Typing :: Typed
Requires-Python: >=3.11
License-File: LICENSE.txt
Dynamic: license-file
